pretix_cashpayment/__init__.py
pretix_cashpayment/apps.py
pretix_cashpayment/payment.py
pretix_cashpayment/signals.py
pretix_cashpayment/locale/de/LC_MESSAGES/django.mo
pretix_cashpayment/locale/de/LC_MESSAGES/django.po
pretix_cashpayment/locale/de_Informal/LC_MESSAGES/django.mo
pretix_cashpayment/locale/de_Informal/LC_MESSAGES/django.po
pretix_cashpayment/locale/pt_BR/LC_MESSAGES/django.mo
pretix_cashpayment/locale/pt_BR/LC_MESSAGES/django.po
pretix_cashpayment/templates/pretix_cashpayment/checkout_payment_form.html
pretix_cashpayment/templates/pretix_cashpayment/control.html
pretix_cashpayment/templates/pretix_cashpayment/pending.html
pretix_cashpayment/templates/pretix_cashpayment/email/order_pending.txt
pretix_cashpayment-2.1.0.dist-info/LICENSE
pretix_cashpayment-2.1.0.dist-info/METADATA
pretix_cashpayment-2.1.0.dist-info/WHEEL
pretix_cashpayment-2.1.0.dist-info/entry_points.txt
pretix_cashpayment-2.1.0.dist-info/top_level.txt
pretix_cashpayment-2.1.0.dist-info/RECORD
