Metadata-Version: 2.1
Name: pretix-cashpayment
Version: 2.1.0
Summary: pretix plugin that allows you to offer your customers a "pay with cash at the venue" option.
Author-email: Martin Gross <martin@pc-coholic.de>
Maintainer-email: Martin Gross <martin@pc-coholic.de>
License: Copyright 2017 Martin Gross
Project-URL: homepage, http://github.com/pc-coholic/pretix-cashpayment
Keywords: pretix
Requires-Python: >=3.9
License-File: LICENSE
